blackbox_py/__init__.py
blackbox_py/client.py
blackbox_py-0.1.0.dist-info/METADATA
blackbox_py-0.1.0.dist-info/WHEEL
blackbox_py-0.1.0.dist-info/top_level.txt
blackbox_py-0.1.0.dist-info/RECORD
