Metadata-Version: 2.4
Name: blackbox-py
Version: 0.1.0
Summary: Lightweight Python client for the BlackBox HTTP API.
Author-email: Skidaux <skidaux@gmail.com>
License: MIT
Project-URL: Repository, https://github.com/Skidaux/blackbox-py
Project-URL: Issues, https://github.com/Skidaux/blackbox-py/issues
Keywords: blackbox,search,client,http
Requires-Python: >=3.8
Provides-Extra: dev
Requires-Dist: pytest; extra == "dev"
